{".class": "MypyFile", "_fullname": "vasp_manager.job_manager", "future_import_flags": [], "is_partial_stub_package": false, "is_stub": false, "names": {".class": "SymbolTable", "JobManager": {".class": "SymbolTableNode", "kind": "Gdef", "node": {".class": "TypeInfo", "_promote": null, "abstract_attributes": [], "bases": ["builtins.object"], "declared_metaclass": null, "defn": {".class": "ClassDef", "fullname": "vasp_manager.job_manager.JobManager", "name": "JobManager", "type_vars": []}, "deletable_attributes": [], "flags": [], "fullname": "vasp_manager.job_manager.JobManager", "has_param_spec_type": false, "metaclass_type": null, "metadata": {}, "module_name": "vasp_manager.job_manager", "mro": ["vasp_manager.job_manager.JobManager", "builtins.object"], "names": {".class": "SymbolTable", "__init__": {".class": "SymbolTableNode", "kind": "Mdef", "node": {".class": "FuncDef", "arg_kinds": [0, 0, 1], "arg_names": ["self", "calc_path", "ignore_personal_errors"], "flags": [], "fullname": "vasp_manager.job_manager.JobManager.__init__", "name": "__init__", "type": null}}, "_check_job_complete": {".class": "SymbolTableNode", "kind": "Mdef", "node": {".class": "FuncDef", "arg_kinds": [0], "arg_names": ["self"], "flags": [], "fullname": "vasp_manager.job_manager.JobManager._check_job_complete", "name": "_check_job_complete", "type": null}}, "_job_complete": {".class": "SymbolTableNode", "implicit": true, "kind": "Mdef", "node": {".class": "Var", "flags": [], "fullname": "vasp_manager.job_manager.JobManager._job_complete", "name": "_job_complete", "type": {".class": "AnyType", "missing_import_name": null, "source_any": null, "type_of_any": 1}}}, "_jobid": {".class": "SymbolTableNode", "implicit": true, "kind": "Mdef", "node": {".class": "Var", "flags": [], "fullname": "vasp_manager.job_manager.JobManager._jobid", "name": "_jobid", "type": {".class": "AnyType", "missing_import_name": null, "source_any": null, "type_of_any": 1}}}, "calc_path": {".class": "SymbolTableNode", "implicit": true, "kind": "Mdef", "node": {".class": "Var", "flags": [], "fullname": "vasp_manager.job_manager.JobManager.calc_path", "name": "calc_path", "type": {".class": "AnyType", "missing_import_name": null, "source_any": null, "type_of_any": 1}}}, "computer": {".class": "SymbolTableNode", "kind": "Mdef", "node": {".class": "Decorator", "func": {".class": "FuncDef", "arg_kinds": [0], "arg_names": ["self"], "flags": ["is_property", "is_decorated"], "fullname": "vasp_manager.job_manager.JobManager.computer", "name": "computer", "type": null}, "is_overload": false, "var": {".class": "Var", "flags": ["is_initialized_in_class", "is_property", "is_settable_property", "is_ready"], "fullname": null, "name": "computer", "type": {".class": "CallableType", "arg_kinds": [0], "arg_names": ["self"], "arg_types": ["vasp_manager.job_manager.JobManager"], "bound_args": [], "def_extras": {"first_arg": "self"}, "fallback": "builtins.function", "from_concatenate": false, "implicit": true, "is_ellipsis_args": false, "name": "computer of JobManager", "ret_type": {".class": "AnyType", "missing_import_name": null, "source_any": null, "type_of_any": 1}, "type_guard": null, "variables": []}}}}, "computing_config_dict": {".class": "SymbolTableNode", "kind": "Mdef", "node": {".class": "Decorator", "func": {".class": "FuncDef", "arg_kinds": [0], "arg_names": ["self"], "flags": ["is_property", "is_decorated"], "fullname": "vasp_manager.job_manager.JobManager.computing_config_dict", "name": "computing_config_dict", "type": null}, "is_overload": false, "var": {".class": "Var", "flags": ["is_initialized_in_class", "is_property", "is_ready"], "fullname": null, "name": "computing_config_dict", "type": {".class": "CallableType", "arg_kinds": [0], "arg_names": ["self"], "arg_types": ["vasp_manager.job_manager.JobManager"], "bound_args": [], "def_extras": {"first_arg": "self"}, "fallback": "builtins.function", "from_concatenate": false, "implicit": true, "is_ellipsis_args": false, "name": "computing_config_dict of JobManager", "ret_type": {".class": "AnyType", "missing_import_name": null, "source_any": null, "type_of_any": 1}, "type_guard": null, "variables": []}}}}, "ignore_personal_errors": {".class": "SymbolTableNode", "implicit": true, "kind": "Mdef", "node": {".class": "Var", "flags": [], "fullname": "vasp_manager.job_manager.JobManager.ignore_personal_errors", "name": "ignore_personal_errors", "type": {".class": "AnyType", "missing_import_name": null, "source_any": null, "type_of_any": 1}}}, "job_complete": {".class": "SymbolTableNode", "kind": "Mdef", "node": {".class": "Decorator", "func": {".class": "FuncDef", "arg_kinds": [0], "arg_names": ["self"], "flags": ["is_property", "is_decorated"], "fullname": "vasp_manager.job_manager.JobManager.job_complete", "name": "job_complete", "type": null}, "is_overload": false, "var": {".class": "Var", "flags": ["is_initialized_in_class", "is_property", "is_ready"], "fullname": null, "name": "job_complete", "type": {".class": "CallableType", "arg_kinds": [0], "arg_names": ["self"], "arg_types": ["vasp_manager.job_manager.JobManager"], "bound_args": [], "def_extras": {"first_arg": "self"}, "fallback": "builtins.function", "from_concatenate": false, "implicit": true, "is_ellipsis_args": false, "name": "job_complete of JobManager", "ret_type": {".class": "AnyType", "missing_import_name": null, "source_any": null, "type_of_any": 1}, "type_guard": null, "variables": []}}}}, "job_exists": {".class": "SymbolTableNode", "kind": "Mdef", "node": {".class": "Decorator", "func": {".class": "FuncDef", "arg_kinds": [0], "arg_names": ["self"], "flags": ["is_property", "is_decorated"], "fullname": "vasp_manager.job_manager.JobManager.job_exists", "name": "job_exists", "type": null}, "is_overload": false, "var": {".class": "Var", "flags": ["is_initialized_in_class", "is_property", "is_ready"], "fullname": null, "name": "job_exists", "type": {".class": "CallableType", "arg_kinds": [0], "arg_names": ["self"], "arg_types": ["vasp_manager.job_manager.JobManager"], "bound_args": [], "def_extras": {"first_arg": "self"}, "fallback": "builtins.function", "from_concatenate": false, "implicit": true, "is_ellipsis_args": false, "name": "job_exists of JobManager", "ret_type": {".class": "AnyType", "missing_import_name": null, "source_any": null, "type_of_any": 1}, "type_guard": null, "variables": []}}}}, "jobid": {".class": "SymbolTableNode", "kind": "Mdef", "node": {".class": "OverloadedFuncDef", "flags": ["is_property"], "fullname": "vasp_manager.job_manager.JobManager.jobid", "impl": null, "items": [{".class": "Decorator", "func": {".class": "FuncDef", "arg_kinds": [0], "arg_names": ["self"], "flags": ["is_property", "is_overload", "is_decorated"], "fullname": "vasp_manager.job_manager.JobManager.jobid", "name": "jobid", "type": null}, "is_overload": true, "var": {".class": "Var", "flags": ["is_initialized_in_class", "is_property", "is_settable_property", "is_ready"], "fullname": null, "name": "jobid", "type": {".class": "CallableType", "arg_kinds": [0], "arg_names": ["self"], "arg_types": ["vasp_manager.job_manager.JobManager"], "bound_args": [], "def_extras": {"first_arg": "self"}, "fallback": "builtins.function", "from_concatenate": false, "implicit": true, "is_ellipsis_args": false, "name": "jobid of JobManager", "ret_type": {".class": "AnyType", "missing_import_name": null, "source_any": null, "type_of_any": 1}, "type_guard": null, "variables": []}}}, {".class": "Decorator", "func": {".class": "FuncDef", "arg_kinds": [0, 0], "arg_names": ["self", "job_value"], "flags": ["is_decorated"], "fullname": "vasp_manager.job_manager.JobManager.jobid", "name": "jobid", "type": null}, "is_overload": false, "var": {".class": "Var", "flags": [], "fullname": null, "name": "jobid", "type": null}}], "type": {".class": "Overloaded", "items": [{".class": "CallableType", "arg_kinds": [0], "arg_names": ["self"], "arg_types": ["vasp_manager.job_manager.JobManager"], "bound_args": [], "def_extras": {"first_arg": "self"}, "fallback": "builtins.function", "from_concatenate": false, "implicit": true, "is_ellipsis_args": false, "name": "jobid", "ret_type": {".class": "AnyType", "missing_import_name": null, "source_any": null, "type_of_any": 1}, "type_guard": null, "variables": []}]}}}, "mode": {".class": "SymbolTableNode", "kind": "Mdef", "node": {".class": "Decorator", "func": {".class": "FuncDef", "arg_kinds": [0], "arg_names": ["self"], "flags": ["is_property", "is_decorated"], "fullname": "vasp_manager.job_manager.JobManager.mode", "name": "mode", "type": null}, "is_overload": false, "var": {".class": "Var", "flags": ["is_initialized_in_class", "is_property", "is_settable_property", "is_ready"], "fullname": null, "name": "mode", "type": {".class": "CallableType", "arg_kinds": [0], "arg_names": ["self"], "arg_types": ["vasp_manager.job_manager.JobManager"], "bound_args": [], "def_extras": {"first_arg": "self"}, "fallback": "builtins.function", "from_concatenate": false, "implicit": true, "is_ellipsis_args": false, "name": "mode of JobManager", "ret_type": {".class": "AnyType", "missing_import_name": null, "source_any": null, "type_of_any": 1}, "type_guard": null, "variables": []}}}}, "submit_job": {".class": "SymbolTableNode", "kind": "Mdef", "node": {".class": "FuncDef", "arg_kinds": [0], "arg_names": ["self"], "flags": [], "fullname": "vasp_manager.job_manager.JobManager.submit_job", "name": "submit_job", "type": null}}, "user_id": {".class": "SymbolTableNode", "kind": "Mdef", "node": {".class": "Decorator", "func": {".class": "FuncDef", "arg_kinds": [0], "arg_names": ["self"], "flags": ["is_property", "is_decorated"], "fullname": "vasp_manager.job_manager.JobManager.user_id", "name": "user_id", "type": null}, "is_overload": false, "var": {".class": "Var", "flags": ["is_initialized_in_class", "is_property", "is_settable_property", "is_ready"], "fullname": null, "name": "user_id", "type": {".class": "CallableType", "arg_kinds": [0], "arg_names": ["self"], "arg_types": ["vasp_manager.job_manager.JobManager"], "bound_args": [], "def_extras": {"first_arg": "self"}, "fallback": "builtins.function", "from_concatenate": false, "implicit": true, "is_ellipsis_args": false, "name": "user_id of JobManager", "ret_type": {".class": "AnyType", "missing_import_name": null, "source_any": null, "type_of_any": 1}, "type_guard": null, "variables": []}}}}}, "slots": null, "tuple_type": null, "type_vars": [], "typeddict_type": null}}, "__annotations__": {".class": "SymbolTableNode", "kind": "Gdef", "node": {".class": "Var", "flags": ["is_ready"], "fullname": "vasp_manager.job_manager.__annotations__", "name": "__annotations__", "type": {".class": "Instance", "args": ["builtins.str", {".class": "AnyType", "missing_import_name": null, "source_any": null, "type_of_any": 6}], "type_ref": "builtins.dict"}}}, "__doc__": {".class": "SymbolTableNode", "kind": "Gdef", "node": {".class": "Var", "flags": ["is_ready"], "fullname": "vasp_manager.job_manager.__doc__", "name": "__doc__", "type": "builtins.str"}}, "__file__": {".class": "SymbolTableNode", "kind": "Gdef", "node": {".class": "Var", "flags": ["is_ready"], "fullname": "vasp_manager.job_manager.__file__", "name": "__file__", "type": "builtins.str"}}, "__name__": {".class": "SymbolTableNode", "kind": "Gdef", "node": {".class": "Var", "flags": ["is_ready"], "fullname": "vasp_manager.job_manager.__name__", "name": "__name__", "type": "builtins.str"}}, "__package__": {".class": "SymbolTableNode", "kind": "Gdef", "node": {".class": "Var", "flags": ["is_ready"], "fullname": "vasp_manager.job_manager.__package__", "name": "__package__", "type": "builtins.str"}}, "cached_property": {".class": "SymbolTableNode", "cross_ref": "functools.cached_property", "kind": "Gdef"}, "change_directory": {".class": "SymbolTableNode", "cross_ref": "vasp_manager.utils.change_directory", "kind": "Gdef"}, "json": {".class": "SymbolTableNode", "cross_ref": "json", "kind": "Gdef"}, "logger": {".class": "SymbolTableNode", "kind": "Gdef", "node": {".class": "Var", "flags": ["has_explicit_value"], "fullname": "vasp_manager.job_manager.logger", "name": "logger", "type": "logging.Logger"}}, "logging": {".class": "SymbolTableNode", "cross_ref": "logging", "kind": "Gdef"}, "subprocess": {".class": "SymbolTableNode", "cross_ref": "subprocess", "kind": "Gdef"}}, "path": "/Users/dalegaines/Documents/github/vasp_manager/vasp_manager/job_manager.py"}